flask_cacheify.py
Flask_Heroku_Cacheify-1.6.0.dist-info/DESCRIPTION.rst
Flask_Heroku_Cacheify-1.6.0.dist-info/METADATA
Flask_Heroku_Cacheify-1.6.0.dist-info/RECORD
Flask_Heroku_Cacheify-1.6.0.dist-info/WHEEL
Flask_Heroku_Cacheify-1.6.0.dist-info/metadata.json
Flask_Heroku_Cacheify-1.6.0.dist-info/top_level.txt
