Metadata-Version: 2.0
Name: Flask-Heroku-Cacheify
Version: 1.6.0
Summary: Automatic Flask cache configuration on Heroku.
Home-page: https://github.com/rdegges/flask-heroku-cacheify
Author: Randall Degges
Author-email: rdegges@gmail.com
License: UNLICENSE
Keywords: flask heroku cloud cache memcache memcached redis awesome
Platform: UNKNOWN
Requires-Dist: Flask-Cache (>=0.11.1)
Requires-Dist: pylibmc (>=1.2.3)
Requires-Dist: redis (>=2.7.2)
